mkinf/__init__.py
mkinf/mkinf.py
mkinf/hub/__init__.py
mkinf/hub/pull.py
mkinf-0.1.8.dist-info/METADATA
mkinf-0.1.8.dist-info/WHEEL
mkinf-0.1.8.dist-info/licenses/LICENSE
mkinf-0.1.8.dist-info/RECORD
