Metadata-Version: 2.4
Name: mkinf
Version: 0.1.8
Summary: mkinf python SDK
Author-email: mkinf <info@mkinf.io>
License-File: LICENSE
Requires-Python: >=3.9
Requires-Dist: langchain-core<0.4,>=0.3.31
Requires-Dist: pydantic<3,>=2.10.5
Requires-Dist: python-dotenv<2,>=1.0.1
Requires-Dist: requests<3,>=2.32.3
Requires-Dist: toml>=0.10.2
